proxystr/__init__.py
proxystr/adapter.py
proxystr/client.py
proxystr/extended_proxy.py
proxystr/proxy.py
proxystr/utils.py
proxystr-2.1.2.dist-info/LICENSE
proxystr-2.1.2.dist-info/METADATA
proxystr-2.1.2.dist-info/WHEEL
proxystr-2.1.2.dist-info/RECORD
