Metadata-Version: 2.1
Name: proxystr
Version: 2.1.2
Summary: Use a proxy as a string, but achieve broad functionality for various scenarios
Home-page: https://github.com/BotsForge/proxystr
License: MIT
Author: MrSmith06
Author-email: sletars@gmail.com
Requires-Python: >=3.8,<4.0
Classifier: License :: OSI Approved :: MIT License
Classifier: Programming Language :: Python :: 3
Classifier: Programming Language :: Python :: 3.8
Classifier: Programming Language :: Python :: 3.9
Classifier: Programming Language :: Python :: 3.10
Classifier: Programming Language :: Python :: 3.11
Classifier: Programming Language :: Python :: 3.12
Requires-Dist: httpx (>=0.27,<0.28)
Requires-Dist: httpx-socks (>=0.9,<0.10)
Requires-Dist: pydantic (>=2.0,<3.0)
Project-URL: Repository, https://github.com/BotsForge/proxystr
